{"api_version":"oam.wasmcloud.dev\/v1","kind":"Application","metadata":{"name":"mlolo"},"cluster":{"name":"clolo","nats-url":"nats:\/\/localhost:4222","workers":[{"id":"worker631","zone":"zone-a","label":null}],"leafs":{"id":"leaf632","zone":"zone-a","label":null}},"components":[{"name":"Http-component","type":"component","image":"ghcr.io\/wasmcloud\/components\/dog-fetcher-rust:0.1.1","replicas":1,"traits":[{"type":"spreadscaler","properties":[{"name":"eastcost","weight":80,"requirement":{"zone":"us-eastcost"}},{"name":"westcost","weight":20,"requirement":{"zone":"us-westcost"}}]},{"type":"link","target":"Httpserver"}]}],"providers":[{"name":"Httpserver","image":"ghcr.io\/wasmcloud\/http-server:0.27.0","traits":[{"type":"link","target":"Http-component"}]}]}